{
  "summary": {
    "original_count": 12858,
    "removed_count": 528,
    "kept_count": 12330,
    "removal_rate": 4.106392907139524,
    "timestamp": "2025-07-24T17:53:37.238948"
  },
  "removal_reasons": {
    "Citation year (2020)": 23,
    "Citation year (2023)": 18,
    "Citation year (2024)": 18,
    "Citation year (2021)": 17,
    "Citation year (2022)": 17,
    "Citation year (2018)": 17,
    "Citation year (2019)": 16,
    "Citation year (2017)": 11,
    "COVID-19 compound term": 8,
    "Pp reference (5.0)": 8,
    "Very low confidence (0.25)": 8,
    "Citation year (2011)": 7,
    "Citation year (2014)": 6,
    "Table reference (3.0)": 6,
    "Chart reference (2025.0)": 6,
    "Pp reference (19.0)": 6,
    "Figure reference (3.0)": 6,
    "Pp reference (2.0)": 5,
    "Pp reference (6.0)": 5,
    "Citation year (2025)": 5,
    "Pp reference (40.0)": 5,
    "Citation year (2012)": 5,
    "Citation year (2015)": 5,
    "Figure reference (4.0)": 5,
    "Multiple validation issues (3)": 5,
    "Pp reference (1.0)": 4,
    "Citation year (2016)": 4,
    "Citation year (2003)": 4,
    "Pp reference (10.0)": 4,
    "Figure reference (9.0)": 4,
    "Table reference (1.0)": 4,
    "Chapter reference (3.0)": 3,
    "Pp reference (58.0)": 3,
    "Pp reference (14.0)": 3,
    "Pp reference (50.0)": 3,
    "Chapter reference (2.0)": 3,
    "Table reference (2.0)": 3,
    "Figure reference (5.0)": 3,
    "Pp reference (47.0)": 3,
    "Figure reference (7.0)": 3,
    "Figure reference (6.0)": 3,
    "Citation year (2001)": 3,
    "Section reference (5.0)": 3,
    "Figure reference (16.0)": 3,
    "Figure reference (3.14)": 2,
    "Pp reference (41.0)": 2,
    "Table reference (3.9)": 2,
    "Pp reference (70.0)": 2,
    "Pp reference (13.8)": 2,
    "Pp reference (78.0)": 2,
    "Pp reference (13.0)": 2,
    "Pp reference (12.0)": 2,
    "Pp reference (52.0)": 2,
    "Citation year (2010)": 2,
    "Table reference (3.8)": 2,
    "Figure reference (4.2)": 2,
    "Pp reference (11.1)": 2,
    "Figure reference (2.0)": 2,
    "Chapter reference (4.0)": 2,
    "Figure reference (12.0)": 2,
    "Pp reference (20.0)": 2,
    "Pp reference (54.0)": 2,
    "Pp reference (34.0)": 2,
    "Pp reference (8.0)": 2,
    "Table reference (5.0)": 2,
    "Graph reference (24.0)": 2,
    "Pp reference (7.5)": 2,
    "Section reference (5.2)": 2,
    "Figure reference (100.0)": 2,
    "Pp reference (9.0)": 2,
    "Page reference (115.0)": 2,
    "Chapter reference (1.0)": 2,
    "Fortune 500/S&P 500 reference": 2,
    "Page reference (298.0)": 2,
    "Citation year (2013)": 2,
    "Section reference (3.0)": 2,
    "Section reference (6.0)": 2,
    "Para reference (2019.0)": 2,
    "Pp reference (17.0)": 2,
    "Figure reference (14.0)": 2,
    "Pp reference (48.3)": 2,
    "Figure reference (13.0)": 2,
    "Pp reference (830.0)": 2,
    "Graph reference (5.0)": 2,
    "Pp reference (840.0)": 1,
    "Table reference (4.2)": 1,
    "Table reference (3.2)": 1,
    "Figure reference (6.6)": 1,
    "Figure reference (3.21)": 1,
    "Section reference (4.1)": 1,
    "Exhibit reference (1.0)": 1,
    "Pp reference (185.0)": 1,
    "Figure reference (1.1)": 1,
    "Pp reference (123.0)": 1,
    "Pp reference (174.0)": 1,
    "Pp reference (92.0)": 1,
    "Pp reference (103.0)": 1,
    "Page reference (27.0)": 1,
    "Graph reference (29.0)": 1,
    "Table reference (0.67)": 1,
    "Pp reference (15.0)": 1,
    "Page reference (20.0)": 1,
    "Page reference (8.0)": 1,
    "Para reference (5.0)": 1,
    "Pp reference (3.0)": 1,
    "Figure reference (11.0)": 1,
    "Exhibit reference (12.0)": 1,
    "Para reference (1.5)": 1,
    "Table reference (4.1)": 1,
    "Chapter reference (6.0)": 1,
    "Figure reference (3.24)": 1,
    "Para reference (3.0)": 1,
    "Para reference (4.0)": 1,
    "Page reference (26.0)": 1,
    "Figure reference (2.1)": 1,
    "Exhibit reference (6.0)": 1,
    "Pp reference (186.0)": 1,
    "Pp reference (7.9)": 1,
    "Page reference (266.0)": 1,
    "Page reference (276.0)": 1,
    "Page reference (113.0)": 1,
    "Pp reference (1.5)": 1,
    "Exhibit reference (11.0)": 1,
    "Page reference (25.0)": 1,
    "Page reference (21.0)": 1,
    "Page reference (1081.0)": 1,
    "Page reference (1088.0)": 1,
    "Section reference (3.4)": 1,
    "Section reference (3.3)": 1,
    "Pp reference (189.0)": 1,
    "Graph reference (2018.0)": 1,
    "Graph reference (2015.0)": 1,
    "Graph reference (2019.0)": 1,
    "Pp reference (30.0)": 1,
    "Pp reference (27.0)": 1,
    "Page reference (47.0)": 1,
    "Page reference (43.0)": 1,
    "Pp reference (217.0)": 1,
    "Exhibit reference (3.0)": 1,
    "Citation year (2004)": 1,
    "Page reference (444.0)": 1,
    "Page reference (436.0)": 1,
    "Page reference (142.0)": 1,
    "Graph reference (21.0)": 1,
    "Pp reference (260.0)": 1,
    "Chapter reference (153.0)": 1,
    "Page reference (83.0)": 1,
    "Page reference (57.0)": 1,
    "Page reference (307.0)": 1,
    "Pp reference (430.0)": 1,
    "Citation year (2000)": 1,
    "Exhibit reference (4.0)": 1,
    "Pp reference (168.0)": 1,
    "Page reference (1498.0)": 1,
    "Section reference (4.4)": 1,
    "Page reference (562.0)": 1,
    "Page reference (128.0)": 1,
    "Page reference (137.0)": 1,
    "Page reference (318.0)": 1,
    "Page reference (74.0)": 1,
    "Page reference (84.0)": 1,
    "Page reference (1512.0)": 1,
    "Exhibit reference (13.0)": 1,
    "Citation year (2009)": 1,
    "Figure reference (17.0)": 1,
    "Figure reference (18.0)": 1,
    "Figure reference (19.0)": 1,
    "Figure reference (20.0)": 1,
    "Figure reference (22.0)": 1,
    "Fig reference (23.0)": 1,
    "Figure reference (24.0)": 1,
    "Figure reference (15.0)": 1,
    "Chapter reference (5.0)": 1,
    "Page reference (450.0)": 1,
    "Page reference (461.0)": 1,
    "Citation year (2007)": 1,
    "Page reference (17.0)": 1,
    "Figure reference (6.2)": 1,
    "Exhibit reference (2.0)": 1,
    "Figure reference (8.0)": 1,
    "Chapter reference (14.0)": 1,
    "Chapter reference (5.3)": 1,
    "Citation year (2006)": 1,
    "Citation year (2002)": 1,
    "Figure reference (26.0)": 1,
    "Figure reference (25.0)": 1,
    "Figure reference (27.0)": 1,
    "Page reference (252.0)": 1,
    "Page reference (246.0)": 1,
    "Figure reference (21.0)": 1,
    "Figure reference (1.0)": 1,
    "Section reference (7.0)": 1,
    "Table reference (9.0)": 1,
    "Page reference (282.0)": 1,
    "Page reference (237.0)": 1,
    "Chapter reference (12.0)": 1,
    "Page reference (1171.0)": 1,
    "Page reference (1043.0)": 1,
    "Page reference (306.0)": 1,
    "Page reference (349.0)": 1,
    "Page reference (390.0)": 1,
    "Page reference (146.0)": 1,
    "Page reference (229.0)": 1,
    "Page reference (214.0)": 1,
    "Exhibit reference (7.0)": 1,
    "Page reference (15.0)": 1,
    "Graph reference (222.0)": 1,
    "Citation year (2005)": 1,
    "Graph reference (2003.0)": 1,
    "Pp reference (510.0)": 1,
    "Section reference (2.0)": 1,
    "Page reference (2024.0)": 1,
    "Figure reference (10.0)": 1,
    "Pp reference (316.0)": 1,
    "Chapter reference (214.0)": 1,
    "Chapter reference (364.0)": 1,
    "Chapter reference (431.0)": 1,
    "Chapter reference (454.0)": 1,
    "Chapter reference (163.0)": 1,
    "Section reference (3911.0)": 1,
    "Section reference (3912.0)": 1,
    "Chapter reference (397.0)": 1,
    "Chapter reference (367.0)": 1,
    "Chapter reference (217.0)": 1,
    "Graph reference (275.0)": 1,
    "Graph reference (337.0)": 1,
    "Chapter reference (326.0)": 1,
    "Chapter reference (283.0)": 1,
    "Pp reference (287.0)": 1,
    "Table reference (52911.0)": 1,
    "Pp reference (67.0)": 1
  },
  "preservation_reasons": {
    "ICT sector data": 833,
    "ICT context detected": 190,
    "Legitimate small number (1.0)": 29,
    "Legitimate small number (4.0)": 19,
    "Legitimate small number (2.0)": 16,
    "Legitimate small number (9.0)": 13,
    "Legitimate small number (3.0)": 13,
    "Legitimate small number (7.0)": 13,
    "Legitimate small number (0.0)": 11,
    "Legitimate small number (12.0)": 10,
    "Legitimate small number (10.0)": 10,
    "Legitimate small number (19.0)": 10,
    "Legitimate small number (8.0)": 9,
    "Meaningful zero from survey/study": 8,
    "Legitimate small number (11.0)": 8,
    "Legitimate small number (5.0)": 7,
    "Legitimate small number (6.0)": 6,
    "Legitimate small number (16.0)": 6,
    "Legitimate small number (17.0)": 6,
    "Legitimate small number (18.0)": 5,
    "Legitimate small number (14.0)": 4,
    "Legitimate small number (6.1)": 3,
    "Legitimate small number (4.3)": 3,
    "Legitimate small number (15.0)": 3,
    "Legitimate small number (9.5)": 2,
    "Legitimate small number (1.7)": 2,
    "Legitimate small number (2.5)": 2,
    "Legitimate small number (9.3)": 2,
    "Legitimate small number (3.4)": 2,
    "Legitimate small number (17.8)": 2,
    "Legitimate small number (3.1)": 1,
    "Legitimate small number (6.3)": 1,
    "Valid SME definition (500.0 employees)": 1,
    "Valid SME definition (50.0 employees)": 1,
    "Legitimate small number (6.13)": 1,
    "Legitimate small number (1.6)": 1,
    "Legitimate small number (13.0)": 1,
    "Legitimate small number (1.8)": 1,
    "Legitimate small number (0.103)": 1,
    "Legitimate small number (0.02)": 1,
    "Legitimate small number (7.5)": 1,
    "Legitimate small number (10.1162)": 1,
    "Legitimate small number (2.018)": 1,
    "Legitimate small number (0.05)": 1,
    "Legitimate small number (1.1)": 1,
    "Legitimate small number (3.8)": 1,
    "Legitimate small number (12.4)": 1,
    "Legitimate small number (3.7)": 1,
    "Legitimate small number (3.6)": 1,
    "Legitimate small number (4.2)": 1,
    "Legitimate small number (4.4)": 1
  },
  "samples": {
    "removed": [
      {
        "metric_id": 2316,
        "value": 19.0,
        "unit": "number",
        "metric_type": "net_employment_change",
        "context": "net 2021 03 google-and-the-university-of-oxford-launch-global-covid-19-tracker-platform  195 https:  news.uchicago.edu story uchicago-joins-new-academicindustry-consortium-accelerate-ai-innovation 196",
        "reason": "COVID-19 compound term"
      },
      {
        "metric_id": 4087,
        "value": 840.0,
        "unit": "number",
        "metric_type": "ai_implementation_count",
        "context": "Enterprise size and the probability of adopting an AI application across 840 enterprises in G7 countries, 2022-23 72 Table 3.4. The intensity of enterprises  spending on R D for AI across 840 enterpri",
        "reason": "Pp reference (840.0)"
      },
      {
        "metric_id": 4103,
        "value": 4.2,
        "unit": "number",
        "metric_type": "ai_implementation_count",
        "context": "Institutions interviewed for this study and the diffusion mechanisms they use 101 Table 4.2. AI Singapore s AI Readiness Index 107 Table 4.3. Sample catalogues of AI applications, use cases and experi",
        "reason": "Table reference (4.2)"
      },
      {
        "metric_id": 7915,
        "value": 2023.0,
        "unit": "number",
        "metric_type": "workforce_augmentation",
        "context": ", and Daniel Schwarcz,  AI Assistance in Legal Analysis: An Empirical Study,  SSRN working paper, 2023. https:  doi.org 10.2139 ssrn.4 539836 Chui, Michael , Bryce Hall, Alex Singla, and Alex Sukharev",
        "reason": "Citation year (2023)"
      },
      {
        "metric_id": 4083,
        "value": 3.2,
        "unit": "number",
        "metric_type": "ai_implementation_count",
        "context": "The 11 applications of AI considered in the 2022-23 OECD BCG INSEAD Survey of AI-Adopting Enterprises 67 Table 3.2. Average number of active AI uses across 840 enterprises by G7 country and industry, ",
        "reason": "Table reference (3.2)"
      },
      {
        "metric_id": 8031,
        "value": 2021.0,
        "unit": "number",
        "metric_type": "ai_implementation_count",
        "context": "Hofman, Jennifer Wortman Vaughan, and Hanna Wallach,  Manipulating and Measuring Model Interpretability,  in Proceedings of the 2021 CHI Conference on Human Factors in Computing Systems, CHI  21 , (Ne",
        "reason": "Citation year (2021)"
      },
      {
        "metric_id": 8027,
        "value": 2023.0,
        "unit": "number",
        "metric_type": "workforce_augmentation",
        "context": "Perry, Neil , Megha Srivastava, Deepak Kumar, and Dan Boneh,  Do Users Write More Insecure Code with AI Assistants ,  in Proceedings of the 2023 ACM SIGSAC Conference on Computer and Communications Se",
        "reason": "Citation year (2023)"
      },
      {
        "metric_id": 5359,
        "value": 2.0,
        "unit": "number",
        "metric_type": "ai_implementation_count",
        "context": "In its mission statement, it pledges to support: 1) investments in developing AI applications across supply chains  2) the commercialisation of AI- powered solutions  3) the AI start-up ecosystem  4) ",
        "reason": "Pp reference (2.0)"
      },
      {
        "metric_id": 4272,
        "value": 6.6,
        "unit": "count",
        "metric_type": "ai_implementation_count",
        "context": "Use of or familiarity with data management solutions among firms surveyed in the state of S\u00e3o Paulo, 2023 137 Figure 6.6. Practices to adopt and develop AI among firms surveyed in the state of S\u00e3o Pau",
        "reason": "Figure reference (6.6)"
      },
      {
        "metric_id": 4244,
        "value": 3.21,
        "unit": "number",
        "metric_type": "workforce_augmentation",
        "context": "Obstacles to the use of cloud computing by industry and enterprise size, across 840 enterprises in G7 countries, 2022-23 86 Figure 3.21. Use of public services supporting the adoption of AI across 840",
        "reason": "Figure reference (3.21)"
      }
    ],
    "preserved": []
  }
}