{
  "source_id": 6,
  "source_name": "Assessing the Impact of Artificial Intelligence Tools on Employee.pdf",
  "timestamp": "2025-07-23T15:05:54.155226",
  "schema_version": "1.1",
  "total_records": 374,
  "kept_records": 100,
  "removed_records": 264,
  "modified_records": 10,
  "duplicate_groups": 111,
  "duplicates_removed": 263,
  "removal_reasons": {
    "Duplicate record": 263,
    "Financial units should not appear with employment metrics": 1
  },
  "modification_types": {
    "general_rate \u2192 adoption_metric": 4,
    "general_rate \u2192 productivity_metric": 3,
    "general_rate \u2192 employment_metric": 3
  },
  "confidence_distribution": {
    "high": 264,
    "medium": 110,
    "low": 0,
    "high_pct": 70.6,
    "medium_pct": 29.4,
    "low_pct": 0.0
  },
  "quality_metrics": {
    "quality_score": 26.74,
    "issues_found": 274,
    "removal_rate": 70.59,
    "modification_rate": 2.67
  },
  "top_removal_reason": "Duplicate record",
  "top_removal_count": 263
}